{
  "mixing_plan": [
    {
      "from_track": null,
      "to_track": "Favourite Girl",
      "incoming_start_sec": 0.0,
      "start_time": "00:00:00",
      "chorus_start_sec": null,
      "chorus_end_sec": null,
      "outgoing_fade_start_sec": null,
      "overlap_sec": 0.0,
      "fade_duration": 2.0,
      "transition_type": "Fade In",
      "bpm_diff_vs_avg": 0,
      "comment": "Start with Favourite Girl (BPM 95)"
    },
    {
      "from_track": "Favourite Girl",
      "to_track": "Tipsy",
      "incoming_start_sec": 40.216961451247165,
      "start_time": "00:00:40",
      "chorus_start_sec": 40.216961451247165,
      "chorus_end_sec": 69.6366439909297,
      "outgoing_fade_start_sec": 69.6366439909297,
      "overlap_sec": 29.419682539682533,
      "fade_duration": 2.0,
      "transition_type": "Chorus Beatmatch",
      "bpm_diff_vs_avg": 0.0,
      "comment": "Favourite Girl (BPM 95) -> Tipsy (BPM 95, chorus 40.2-69.6s, BPM diff vs avg 0.0)"
    },
    {
      "from_track": "Tipsy",
      "to_track": "Work Me Out (feat. Wizkid) (Official Music Video)",
      "incoming_start_sec": 113.69650793650794,
      "start_time": "00:01:53",
      "chorus_start_sec": 73.47954648526077,
      "chorus_end_sec": 99.86902494331066,
      "outgoing_fade_start_sec": 140.08598639455784,
      "overlap_sec": 26.389478458049894,
      "fade_duration": 2.0,
      "transition_type": "Chorus Beatmatch",
      "bpm_diff_vs_avg": 6.666666666666671,
      "comment": "Tipsy (BPM 95) -> Work Me Out (feat. Wizkid) (Official Music Video) (BPM 105, chorus 73.5-99.9s, BPM diff vs avg 6.7)"
    },
    {
      "from_track": "Work Me Out (feat. Wizkid) (Official Music Video)",
      "to_track": "Love Me JeJe (Lyrics)",
      "incoming_start_sec": 164.01414965986396,
      "start_time": "00:02:44",
      "chorus_start_sec": 50.31764172335601,
      "chorus_end_sec": 82.24507936507936,
      "outgoing_fade_start_sec": 195.9415873015873,
      "overlap_sec": 31.92743764172335,
      "fade_duration": 2.0,
      "transition_type": "Chorus Beatmatch",
      "bpm_diff_vs_avg": 5.0,
      "comment": "Work Me Out (feat. Wizkid) (Official Music Video) (BPM 105) -> Love Me JeJe (Lyrics) (BPM 105, chorus 50.3-82.2s, BPM diff vs avg 5.0)"
    },
    {
      "from_track": "Love Me JeJe (Lyrics)",
      "to_track": "Jump (Lyrics) ft. Gunna, Skillibeng",
      "incoming_start_sec": 342.2040816326531,
      "start_time": "00:05:42",
      "chorus_start_sec": 49.5978231292517,
      "chorus_end_sec": 80.89832199546485,
      "outgoing_fade_start_sec": 340.2040816326531,
      "overlap_sec": 178.1899319727891,
      "fade_duration": 2.0,
      "transition_type": "Full Song + Crossfade",
      "bpm_diff_vs_avg": 4.0,
      "comment": "Every 5th song: Play full 'Love Me JeJe (Lyrics)' then crossfade into 'Jump (Lyrics) ft. Gunna, Skillibeng' (BPM diff vs avg 4.0)"
    },
    {
      "from_track": "Jump (Lyrics) ft. Gunna, Skillibeng",
      "to_track": "Nasty OFFICIAL VERSION",
      "incoming_start_sec": 389.86303854875285,
      "start_time": "00:06:29",
      "chorus_start_sec": 47.658956916099775,
      "chorus_end_sec": 73.22412698412698,
      "outgoing_fade_start_sec": 415.42820861678007,
      "overlap_sec": 25.565170068027207,
      "fade_duration": 2.0,
      "transition_type": "Chorus Beatmatch",
      "bpm_diff_vs_avg": 4.400000000000006,
      "comment": "Jump (Lyrics) ft. Gunna, Skillibeng (BPM 105) -> Nasty OFFICIAL VERSION (BPM 108, chorus 47.7-73.2s, BPM diff vs avg 4.4)"
    },
    {
      "from_track": "Nasty OFFICIAL VERSION",
      "to_track": "Needle",
      "incoming_start_sec": 445.9740589569161,
      "start_time": "00:07:25",
      "chorus_start_sec": 56.11102040816326,
      "chorus_end_sec": 87.30702947845805,
      "outgoing_fade_start_sec": 477.1700680272109,
      "overlap_sec": 31.196009070294785,
      "fade_duration": 2.0,
      "transition_type": "Chorus Beatmatch",
      "bpm_diff_vs_avg": 30.599999999999994,
      "comment": "Nasty OFFICIAL VERSION (BPM 108) -> Needle (BPM 144, chorus 56.1-87.3s, BPM diff vs avg 30.6)"
    }
  ]
}