{
  "structure_setlist": [
    {
      "time": "00:00\u201301:00",
      "tracks": [
        {
          "title": "Favourite Girl",
          "artist": "Unknown",
          "file": "Favourite Girl.mp3",
          "has_vocals": true,
          "transition_point": 62.9
        },
        {
          "title": "Needle",
          "artist": "Unknown",
          "file": "Needle.mp3",
          "has_vocals": true,
          "transition_point": 65.44
        },
        {
          "title": "Work Me Out (feat. Wizkid) (Official Music Video)",
          "artist": "Shenseea",
          "file": "Shenseea - Work Me Out (feat. Wizkid) (Official Music Video).mp3",
          "has_vocals": true,
          "transition_point": 74.9
        },
        {
          "title": "Love Me JeJe (Lyrics)",
          "artist": "Tems",
          "file": "Tems - Love Me JeJe (Lyrics).mp3",
          "has_vocals": true,
          "transition_point": 85.41999816894531
        },
        {
          "title": "Nasty OFFICIAL VERSION",
          "artist": "Tinashe",
          "file": "Tinashe - Nasty OFFICIAL VERSION.mp3",
          "has_vocals": true,
          "transition_point": 68.08
        },
        {
          "title": "Tipsy",
          "artist": "Unknown",
          "file": "Tipsy.mp3",
          "has_vocals": true,
          "transition_point": 82.76
        },
        {
          "title": "Jump (Lyrics) ft. Gunna, Skillibeng",
          "artist": "Tyla",
          "file": "Tyla - Jump (Lyrics) ft. Gunna, Skillibeng.mp3",
          "has_vocals": true,
          "transition_point": 63.959999084472656
        }
      ]
    }
  ]
}